<?xml version="1.0" encoding="utf-8"?>
<updates>
    <update>
        <name>Health Checker for Joomla</name>
        <description>A comprehensive health check extension for Joomla</description>
        <element>pkg_healthchecker</element>
        <type>package</type>
        <client>site</client>
        <version>3.8.2</version>
        <infourl title="Health Checker">https://github.com/mySites-guru/HealthCheckerForJoomla</infourl>
        <downloads>
            <downloadurl type="full" format="zip">https://www.joomlahealthchecker.com/downloads/pkg_healthchecker-3.8.2.zip</downloadurl>
        </downloads>
        <sha512>2f672772991cd142b012adc264f01eb6bae131910c4ba1723d4dbdc68200156763db31e7701608749060b6c6a0a333d30fb0072edc3bb7c245ec2656d234dc67</sha512>
        <tags>
            <tag>stable</tag>
        </tags>
        <maintainer>mySites.guru / Phil E. Taylor</maintainer>
        <maintainerurl>https://www.phil-taylor.com</maintainerurl>
        <targetplatform name="joomla" version="(5|6)\.[0-9]+" />
        <php_minimum>8.1.0</php_minimum>
    </update>
</updates>
